print2/__init__.py
print2/print2.py
print2-0.2.9.dist-info/LICENSE
print2-0.2.9.dist-info/METADATA
print2-0.2.9.dist-info/WHEEL
print2-0.2.9.dist-info/top_level.txt
print2-0.2.9.dist-info/RECORD
