Metadata-Version: 2.1
Name: print2
Version: 0.2.9
Summary: Print2 helps print beautiful message with indent and color
Author-email: Jeremie Robert <appydo@gmail.com>
License: MIT License
Project-URL: Homepage, https://github.com/jerob/print2
Project-URL: documentation, https://github.com/jerob/print2/blob/main/README.md
Project-URL: Bug Tracker, https://github.com/jerob/print2/issues
Classifier: Programming Language :: Python :: 3
Classifier: License :: OSI Approved :: MIT License
Classifier: Operating System :: OS Independent
Requires-Python: >=3.7
License-File: LICENSE
Provides-Extra: dev
Requires-Dist: black (>=22.12.0) ; extra == 'dev'
